stepshift.py
stepshift-0.3.0.dist-info/WHEEL
stepshift-0.3.0.dist-info/METADATA
stepshift-0.3.0.dist-info/RECORD
