Metadata-Version: 2.1
Name: stepshift
Version: 0.3.0
Summary: Time-step shifting modelling logic, used by the ViEWS team for training models.
License: MIT
Author: peder2911
Author-email: pglandsverk@gmail.com
Requires-Python: >=3.8,<4.0
Classifier: License :: OSI Approved :: MIT License
Classifier: Programming Language :: Python :: 3
Classifier: Programming Language :: Python :: 3.8
Classifier: Programming Language :: Python :: 3.9
Requires-Dist: PyMonad (>=2.4.0,<3.0.0)
Requires-Dist: pandas (>=1.2.4,<2.0.0)
